strength_tracker/__init__.py
strength_tracker/strength_tracker.py
strength_tracker-1.0.0.dist-info/licenses/LICENSE
strength_tracker-1.0.0.dist-info/METADATA
strength_tracker-1.0.0.dist-info/WHEEL
strength_tracker-1.0.0.dist-info/entry_points.txt
strength_tracker-1.0.0.dist-info/top_level.txt
strength_tracker-1.0.0.dist-info/RECORD
